{
  "_template": "cookiepy",
  "author": "Erik Ingwersen",
  "command_line_interface": "No command-line interface",
  "copyright_year": "2023",
  "create_author_file": "y",
  "development_status": "Development Status :: 1 - Planning",
  "email": "erik.ingwersen@br.ey.com",
  "friendly_name": "Better Dict",
  "github_user": "ingwersen-erik",
  "license": "MIT",
  "noarch_python": "y",
  "package_name": "better_dict",
  "project_name": "better-dict",
  "repo_main_branch": "main",
  "setup_py_uses_setuptools_scm": "y",
  "short_description": "Python dictionary revamped.",
  "use_black": "y",
  "use_flake8": "y",
  "use_isort": "y",
  "use_poetry": "y",
  "use_pytest": "y",
  "version": "0.0.1"
}
